ratio_typst/__init__.py
ratio_typst/document.py
ratio_typst-0.1.4.dist-info/METADATA
ratio_typst-0.1.4.dist-info/WHEEL
ratio_typst-0.1.4.dist-info/licenses/LICENSE
ratio_typst-0.1.4.dist-info/RECORD
