Metadata-Version: 2.4
Name: ratio-typst
Version: 0.1.4
Summary: Generate Typst documents from Python using the Ratio theme.
Project-URL: Repository, https://gitlab.com/ratio-case-os/python/ratio-typst
Project-URL: Bug Tracker, https://gitlab.com/ratio-case-os/python/ratio-typst/-/issues
Project-URL: Changelog, https://gitlab.com/ratio-case-os/python/ratio-typst/-/blob/main/CHANGELOG.md
Author-email: "Ratio Innovations B.V." <info@ratio-case.nl>
License-Expression: MIT
License-File: LICENSE
Keywords: document,presentation,report,typesetting,typst
Requires-Python: >=3.11
Requires-Dist: pypst>=0.6.1
Requires-Dist: pyserde[toml]>=0.24.0
